AUTHORS.rst
CONTRIBUTING.rst
HISTORY.rst
LICENSE
MANIFEST.in
README.md
README.rst
requirements_dev.txt
requirments.txt
setup.cfg
setup.py
tox.ini
python_yapi/__init__.py
python_yapi/base.py
python_yapi/cli.py
python_yapi/collection.py
python_yapi/constants.py
python_yapi/exceptions.py
python_yapi/follow.py
python_yapi/group.py
python_yapi/interface.py
python_yapi/log.py
python_yapi/models.py
python_yapi/project.py
python_yapi/user.py
python_yapi/utils.py
python_yapi/yapi.py
python_yapi.egg-info/PKG-INFO
python_yapi.egg-info/SOURCES.txt
python_yapi.egg-info/dependency_links.txt
python_yapi.egg-info/requires.txt
python_yapi.egg-info/top_level.txt
python_yapi.egg-info/zip-safe
tests/test_base_api.py
tests/test_group.py
tests/test_interface.py
tests/test_project.py
tests/test_user.py