Metadata-Version: 2.1
Name: python-yapi
Version: 0.1.3
Summary: python yapi sdk
Home-page: https://github.com/hanzhichao/python-yapi
Author: Han Zhichao
Author-email: superhin@126.com
License: MIT license
Keywords: yapi,python-yapi,pyyapi,yapi-client
Classifier: Programming Language :: Python
Classifier: Programming Language :: Python :: 2.7
Classifier: Programming Language :: Python :: 3.7
License-File: LICENSE
License-File: AUTHORS.rst
